tests/__init__.py
vmapcrawler/__init__.py
vmapcrawler/vmapcrawler.py
vmapcrawler-3.0.5.dist-info/LICENSE.txt
vmapcrawler-3.0.5.dist-info/METADATA
vmapcrawler-3.0.5.dist-info/WHEEL
vmapcrawler-3.0.5.dist-info/top_level.txt
vmapcrawler-3.0.5.dist-info/RECORD
