Metadata-Version: 2.1
Name: vmapcrawler
Version: 3.0.5
Summary: Crawler for Vmap map
Home-page: https://github.com/vuviethung1998/vmapcrawler
Author: Vu Viet Hung
Author-email: vuviethung.98.hust@gmail.com
License: UNKNOWN
Platform: UNKNOWN
Classifier: Programming Language :: Python :: 3
Classifier: Programming Language :: Python :: 3.6
Classifier: Programming Language :: Python :: 3.7
Classifier: License :: OSI Approved :: MIT License
Classifier: Operating System :: OS Independent
